modellogger/__init__.py
modellogger/log_config.py
modellogger/py.typed
airr_modellogger-0.1.2.dist-info/LICENSE.md
airr_modellogger-0.1.2.dist-info/METADATA
airr_modellogger-0.1.2.dist-info/WHEEL
airr_modellogger-0.1.2.dist-info/RECORD
