Metadata-Version: 2.1
Name: airr-modellogger
Version: 0.1.2
Summary: Python logging configuration library for MLCommons AIRR applications.
Home-page: https://github.com/mlcommons/modellogger
Keywords: logging,internal
Author: Daniel Hosterman
Author-email: daniel@mlcommons.org
Requires-Python: >=3.12,<4.0
Classifier: Development Status :: 3 - Alpha
Classifier: Intended Audience :: Developers
Classifier: Programming Language :: Python :: 3
Classifier: Programming Language :: Python :: 3.12
Classifier: Programming Language :: Python :: 3.13
Classifier: Programming Language :: Python :: 3.10
Classifier: Programming Language :: Python :: 3.11
Classifier: Programming Language :: Python :: 3.14
Project-URL: Documentation, https://github.com/mlcommons/modellogger#readme
Project-URL: Repository, https://github.com/mlcommons/modellogger
